eipython/__init__.py
eipython/__main__.py
eipython/core.py
enhanced_ipython-0.0.1.dist-info/LICENSE
enhanced_ipython-0.0.1.dist-info/METADATA
enhanced_ipython-0.0.1.dist-info/WHEEL
enhanced_ipython-0.0.1.dist-info/entry_points.txt
enhanced_ipython-0.0.1.dist-info/top_level.txt
enhanced_ipython-0.0.1.dist-info/RECORD
