Metadata-Version: 2.1
Name: enhanced-ipython
Version: 0.0.1
Summary: An enhanced IPython shell.
Home-page: https://github.com/FrostiiWeeb/enhanced-ipython
Author: Alex Hutz
Author-email: frostiiweeb@gmail.com
License: Copyright (c) 2017, Kenneth Reitz        
Platform: UNKNOWN
License-File: LICENSE
Requires-Dist: aioconsole
Requires-Dist: colorama
Requires-Dist: async-eval
Requires-Dist: prompt-toolkit
Requires-Dist: rich
Requires-Dist: pygments
Requires-Dist: nose
